remhind/__init__.py
remhind/__main__.py
remhind/events.py
remhind/monitor.py
remhind/tests/__init__.py
remhind/tests/test_events.py
remhind-0.1.1.dist-info/LICENSE
remhind-0.1.1.dist-info/METADATA
remhind-0.1.1.dist-info/WHEEL
remhind-0.1.1.dist-info/entry_points.txt
remhind-0.1.1.dist-info/top_level.txt
remhind-0.1.1.dist-info/zip-safe
remhind-0.1.1.dist-info/RECORD
