Metadata-Version: 2.1
Name: remhind
Version: 0.1.1
Summary: A daemon to display notifications of iCalendar events
Home-page: UNKNOWN
Author: Nicolas Évrard
Author-email: nicoe@openhex.org
License: GPL-3
Platform: UNKNOWN
Classifier: License :: OSI Approved :: GNU General Public License v3 (GPLv3)
Classifier: Programming Language :: Python :: 3
Classifier: Operating System :: POSIX
Classifier: Topic :: Utilities
Classifier: Topic :: Office/Business :: Scheduling
Requires-Dist: aionotify
Requires-Dist: icalendar
Requires-Dist: python-dateutil
Requires-Dist: pyinotify
Requires-Dist: PyGObject
Requires-Dist: toml
Requires-Dist: tzlocal
Requires-Dist: xdg
